python_bitvavo_api/__init__.py
python_bitvavo_api/bitvavo.py
python_bitvavo_api/testApi.py
python_bitvavo_api-1.4.3.dist-info/licenses/LICENSE.txt
python_bitvavo_api-1.4.3.dist-info/METADATA
python_bitvavo_api-1.4.3.dist-info/WHEEL
python_bitvavo_api-1.4.3.dist-info/top_level.txt
python_bitvavo_api-1.4.3.dist-info/RECORD
