Metadata-Version: 2.4
Name: python_bitvavo_api
Version: 1.4.3
Summary: Use Bitvavo SDK for Python to buy, sell, and store over 200 digital assets on Bitvavo from inside your app.
Home-page: https://github.com/bitvavo/python-bitvavo-api
Author: Bitvavo
Classifier: Programming Language :: Python :: 3
Classifier: License :: OSI Approved :: ISC License (ISCL)
Classifier: Operating System :: OS Independent
Requires-Python: >=3.6
License-File: LICENSE.txt
Requires-Dist: websocket-client<2.0.0,>=1.6.0
Requires-Dist: requests<3.0.0,>=2.31.0
Requires-Dist: setuptools
Dynamic: author
Dynamic: classifier
Dynamic: description
Dynamic: description-content-type
Dynamic: home-page
Dynamic: license-file
Dynamic: requires-dist
Dynamic: requires-python
Dynamic: summary
